pypads_padre/__init__.py
pypads_padre/app/__init__.py
pypads_padre/app/actuators.py
pypads_padre/app/api.py
pypads_padre/app/backends/__init__.py
pypads_padre/app/backends/repository.py
pypads_padre/app/decorators.py
pypads_padre/app/plugin.py
pypads_padre/app/results.py
pypads_padre/app/validators.py
pypads_padre/arguments.py
pypads_padre/bindings/__init__.py
pypads_padre/bindings/anchors.py
pypads_padre/bindings/event_types.py
pypads_padre/bindings/events.py
pypads_padre/bindings/hooks.py
pypads_padre/bindings/resources/__init__.py
pypads_padre/bindings/resources/mapping/__init__.py
pypads_padre/bindings/resources/mapping/keras_2_3_1.yml
pypads_padre/bindings/resources/mapping/sklearn_0_19_1.yml
pypads_padre/bindings/resources/mapping/tensorflow_2_3_0.yml
pypads_padre/bindings/resources/mapping/torch_1_4_0.yml
pypads_padre/bindings/resources/mapping/torchvision_0_5_0.yml
pypads_padre/concepts/__init__.py
pypads_padre/concepts/dataset.py
pypads_padre/concepts/nlp.py
pypads_padre/concepts/splitter.py
pypads_padre/concepts/util.py
pypads_padre/injections/__init__.py
pypads_padre/injections/analysis/__init__.py
pypads_padre/injections/analysis/doc_parsing.py
pypads_padre/injections/analysis/models.py
pypads_padre/injections/analysis/parameter_search.py
pypads_padre/injections/analysis/parameters.py
pypads_padre/injections/loggers/__init__.py
pypads_padre/injections/loggers/data_splitting.py
pypads_padre/injections/loggers/dataset.py
pypads_padre/injections/loggers/decision_tracking.py
pypads_padre/injections/loggers/estimator.py
pypads_padre/injections/loggers/hyperparameters.py
pypads_padre/injections/loggers/metric.py
pypads_padre/util.py
pypads_padre-0.4.3.dist-info/LICENSE
pypads_padre-0.4.3.dist-info/WHEEL
pypads_padre-0.4.3.dist-info/METADATA
pypads_padre-0.4.3.dist-info/RECORD
