Metadata-Version: 2.1
Name: pypads-padre
Version: 0.4.3
Summary: PyPads_PaDRe aims to to add additional machine learning concepts into the world of pypads.
Home-page: https://www.padre-lab.eu/
License: GPL-3.0-or-later
Keywords: tracking,machine learning,deep learning,neural networks,reproducibility
Author: Thomas Weißgerber
Author-email: thomas.weissgerber@uni-passau.de
Requires-Python: >=3.7.0,<4.0.0
Classifier: Development Status :: 3 - Alpha
Classifier: Intended Audience :: Developers
Classifier: Intended Audience :: Science/Research
Classifier: License :: OSI Approved :: GNU General Public License v3 or later (GPLv3+)
Classifier: Natural Language :: English
Classifier: Operating System :: MacOS
Classifier: Operating System :: Microsoft :: Windows
Classifier: Operating System :: Unix
Classifier: Programming Language :: Python :: 3
Classifier: Programming Language :: Python :: 3.7
Classifier: Programming Language :: Python :: 3.8
Classifier: Programming Language :: Python :: 3.9
Classifier: Topic :: Scientific/Engineering :: Artificial Intelligence
Provides-Extra: docs
Requires-Dist: pypads (>=0.5.7,<0.6.0)
Project-URL: Documentation, https://pypads.readthedocs.io/en/latest/
Project-URL: Repository, https://github.com/padre-lab-eu/pypads-padre
